bottleneck_transformer_flax/__init__.py
bottleneck_transformer_flax/botnet.py
bottleneck_transformer_flax-0.0.1.dist-info/LICENSE
bottleneck_transformer_flax-0.0.1.dist-info/METADATA
bottleneck_transformer_flax-0.0.1.dist-info/WHEEL
bottleneck_transformer_flax-0.0.1.dist-info/top_level.txt
bottleneck_transformer_flax-0.0.1.dist-info/RECORD
