Metadata-Version: 2.1
Name: bottleneck-transformer-flax
Version: 0.0.1
Summary: Bottleneck Transformer - Flax
Home-page: https://github.com/NZ99/bottleneck-transformer-flax
Author: Niccolò Zanichelli
Author-email: niccolo.zanichelli@gmail.com
License: MIT
Keywords: artificial intelligence,deep learning,transformer,image classification
Platform: UNKNOWN
Classifier: Development Status :: 4 - Beta
Classifier: Intended Audience :: Developers
Classifier: Topic :: Scientific/Engineering :: Artificial Intelligence
Classifier: License :: OSI Approved :: MIT License
Classifier: Programming Language :: Python :: 3.6
Requires-Dist: jax
Requires-Dist: jaxlib
Requires-Dist: flax
Requires-Dist: einops (>=0.3)
